setup.cfg
setup.py
calpy/__init__.py
calpy.egg-info/PKG-INFO
calpy.egg-info/SOURCES.txt
calpy.egg-info/dependency_links.txt
calpy.egg-info/requires.txt
calpy.egg-info/top_level.txt
calpy/dsp/__init__.py
calpy/dsp/audio_features.py
calpy/dsp/yin.py
calpy/entropy/__init__.py
calpy/entropy/entropy.py
calpy/plots/__init__.py
calpy/plots/plots.py
calpy/rqa/__init__.py
calpy/rqa/rqa.py
calpy/utilities/__init__.py
calpy/utilities/utilities.py