Metadata-Version: 1.0
Name: calpy
Version: 0.1.4
Summary: Communication Analytics Lab Toolbox
Home-page: https://github.com/YvonneYYu/calpy
Author: ['Yvonne Yu & Paul Vrbik']
Author-email: ['yeyang.yu@uqconnect.edu.au', 'paulvrbik@gmail.com']
License: MIT
Keywords: Natural Language Understanding,Signal Processing
Platform: UNKNOWN
